destipy/__init__.py
destipy/dbase.py
destipy/destiny_client.py
destipy/manifest.py
destipy/oauth.py
destipy/endpoints/__init__.py
destipy/endpoints/app.py
destipy/endpoints/base.py
destipy/endpoints/communitycontent.py
destipy/endpoints/content.py
destipy/endpoints/destiny2.py
destipy/endpoints/fireteam.py
destipy/endpoints/forum.py
destipy/endpoints/groupv2.py
destipy/endpoints/social.py
destipy/endpoints/tokens.py
destipy/endpoints/trending.py
destipy/endpoints/user.py
destipy/utils/__init__.py
destipy/utils/enums.py
destipy/utils/error.py
destipy/utils/http_method.py
destipy/utils/requester.py
destipy/utils/utils_destipy.py
Destipy-0.81.dist-info/LICENSE
Destipy-0.81.dist-info/METADATA
Destipy-0.81.dist-info/WHEEL
Destipy-0.81.dist-info/top_level.txt
Destipy-0.81.dist-info/RECORD
